iust_ai_toolkit/__init__.py
iust_ai_toolkit/abdi_4031/__init__.py
iust_ai_toolkit/abdi_4031/decision_tree_submission/__init__.py
iust_ai_toolkit/abdi_4031/decision_tree_submission/authenticator.py
iust_ai_toolkit/base_authenticator.py
iust_ai_toolkit/cli.py
iust_ai_toolkit-0.1.4.dist-info/METADATA
iust_ai_toolkit-0.1.4.dist-info/WHEEL
iust_ai_toolkit-0.1.4.dist-info/entry_points.txt
iust_ai_toolkit-0.1.4.dist-info/RECORD
