Metadata-Version: 2.1
Name: iust_ai_toolkit
Version: 0.1.4
Summary: A Toolkit for AI course submissions at IUST
Home-page: https://github.com/MSNP1381/iust_ai_toolkit
License: MIT
Author: MSNP
Author-email: mohamadnematpoor@gmail.com
Requires-Python: >=3.12,<4.0
Classifier: Development Status :: 3 - Alpha
Classifier: Intended Audience :: Developers
Classifier: License :: OSI Approved :: MIT License
Classifier: Operating System :: OS Independent
Classifier: Programming Language :: Python :: 3
Classifier: Programming Language :: Python :: 3.12
Classifier: Programming Language :: Python :: 3.10
Classifier: Programming Language :: Python :: 3.11
Classifier: Programming Language :: Python :: 3.7
Classifier: Programming Language :: Python :: 3.8
Classifier: Programming Language :: Python :: 3.9
Provides-Extra: ta
Requires-Dist: click (>=8.1.3,<9.0.0)
Requires-Dist: pandas
Requires-Dist: setuptools
Project-URL: Repository, https://github.com/MSNP1381/iust_ai_toolkit
